{"size": 407454, "filesCount": 16, "files": [{"name": "tutorials.todo.md", "size": 3766, "encoding": "br"}, {"name": "index.md", "size": 2759, "encoding": "br"}, {"name": "tutorials.md", "size": 697, "encoding": "br"}, {"name": "reactivex-icon.png", "size": 173680, "encoding": "identity"}, {"name": "trex.png", "size": 2396, "encoding": "identity"}, {"name": "style-wrong-type.png", "size": 62818, "encoding": "identity"}, {"name": "error-<b>-no-href.png", "size": 34477, "encoding": "identity"}, {"name": "favicon.png", "size": 1913, "encoding": "identity"}, {"name": "inlined-doc.png", "size": 56848, "encoding": "identity"}, {"name": "tutorials.basics.md", "size": 5387, "encoding": "br"}, {"name": "error-wrong-type.png", "size": 45615, "encoding": "identity"}, {"name": "how-to.install.md", "size": 396, "encoding": "br"}, {"name": "how-to.md", "size": 1742, "encoding": "br"}, {"name": "reactivex.svg", "size": 1848, "encoding": "br"}, {"name": "how-to.typings.md", "size": 1405, "encoding": "br"}], "folders": [{"name": "api", "path": "assets/api", "size": 11707, "filesCount": -1}]}