{"size": 34981, "filesCount": 37, "files": [{"name": "WebGPUUniformBuffer.js", "size": 171, "encoding": "br"}, {"name": "WebGPURenderLists.js", "size": 867, "encoding": "br"}, {"name": "WebGPUSampledTexture.js", "size": 367, "encoding": "br"}, {"name": "WebGPUSampler.js", "size": 215, "encoding": "br"}, {"name": "WebGPUProgrammableStage.js", "size": 176, "encoding": "br"}, {"name": "WebGPUBufferUtils.js", "size": 253, "encoding": "br"}, {"name": "WebGPURenderStates.js", "size": 272, "encoding": "br"}, {"name": "WebGPUTextureUtils.js", "size": 1633, "encoding": "br"}, {"name": "WebGPUProperties.js", "size": 194, "encoding": "br"}, {"name": "WebGPUAnimation.js", "size": 261, "encoding": "br"}, {"name": "WebGPUBuffer.js", "size": 315, "encoding": "br"}, {"name": "WebGPUStorageBuffer.js", "size": 194, "encoding": "br"}, {"name": "WebGPUBackground.js", "size": 1082, "encoding": "br"}, {"name": "WebGPUGeometries.js", "size": 929, "encoding": "br"}, {"name": "WebGPURenderTarget.js", "size": 151, "encoding": "br"}, {"name": "WebGPURenderObjects.js", "size": 311, "encoding": "br"}, {"name": "WebGPUAttributes.js", "size": 922, "encoding": "br"}, {"name": "WebGPUUniformsGroup.js", "size": 1031, "encoding": "br"}, {"name": "WebGPURenderObject.js", "size": 305, "encoding": "br"}, {"name": "WebGPUUtils.js", "size": 436, "encoding": "br"}, {"name": "WebGPURenderer.js", "size": 5492, "encoding": "br"}, {"name": "constants.js", "size": 1922, "encoding": "br"}, {"name": "WebGPUWeakMap.js", "size": 274, "encoding": "br"}, {"name": "WebGPUUniform.js", "size": 380, "encoding": "br"}, {"name": "WebGPUInfo.js", "size": 351, "encoding": "br"}, {"name": "WebGPUBindings.js", "size": 1182, "encoding": "br"}, {"name": "WebGPURenderPipeline.js", "size": 3054, "encoding": "br"}, {"name": "WebGPUTextureRenderer.js", "size": 228, "encoding": "br"}, {"name": "WebGPUTextures.js", "size": 4332, "encoding": "br"}, {"name": "WebGPUBinding.js", "size": 145, "encoding": "br"}, {"name": "WebGPURenderPipelines.js", "size": 1478, "encoding": "br"}, {"name": "WebGPUComputePipelines.js", "size": 419, "encoding": "br"}], "folders": [{"name": "nodes", "path": "examples/jsm/renderers/webgpu/nodes", "size": 5639, "filesCount": -1}]}