{"size": 947747, "filesCount": 47, "files": [{"name": "hierarchy.html", "size": 10418, "encoding": "identity"}, {"name": ".nojekyll", "size": 143, "encoding": "identity"}, {"name": "index.html", "size": 7948, "encoding": "identity"}, {"name": "modules.html", "size": 5764, "encoding": "identity"}], "folders": [{"name": "types", "path": "dist/docs/types", "size": 21049, "filesCount": -1}, {"name": "functions", "path": "dist/docs/functions", "size": 18282, "filesCount": -1}, {"name": "assets", "path": "dist/docs/assets", "size": 41955, "filesCount": -1}, {"name": "modules", "path": "dist/docs/modules", "size": 18202, "filesCount": -1}, {"name": "interfaces", "path": "dist/docs/interfaces", "size": 38244, "filesCount": -1}, {"name": "classes", "path": "dist/docs/classes", "size": 766107, "filesCount": -1}, {"name": "variables", "path": "dist/docs/variables", "size": 19635, "filesCount": -1}]}